{
  "links": [
    {
      "url": {
        "protocol": "https:",
        "slashes": true,
        "auth": null,
        "host": "domifa.fabrique.social.gouv.fr",
        "port": null,
        "hostname": "domifa.fabrique.social.gouv.fr",
        "hash": null,
        "search": null,
        "query": null,
        "pathname": "/",
        "path": "/",
        "href": "https://domifa.fabrique.social.gouv.fr/"
      },
      "link": "https://domifa.fabrique.social.gouv.fr/",
      "line": "--2021-09-06 09:41:21--  https://domifa.fabrique.social.gouv.fr/",
      "broken": false
    },
    {
      "url": {
        "protocol": "https:",
        "slashes": true,
        "auth": null,
        "host": "domifa.fabrique.social.gouv.fr",
        "port": null,
        "hostname": "domifa.fabrique.social.gouv.fr",
        "hash": null,
        "search": null,
        "query": null,
        "pathname": "/robots.txt",
        "path": "/robots.txt",
        "href": "https://domifa.fabrique.social.gouv.fr/robots.txt"
      },
      "link": "https://domifa.fabrique.social.gouv.fr/robots.txt",
      "line": "--2021-09-06 09:41:22--  https://domifa.fabrique.social.gouv.fr/robots.txt",
      "broken": false
    },
    {
      "url": {
        "protocol": "https:",
        "slashes": true,
        "auth": null,
        "host": "domifa.fabrique.social.gouv.fr",
        "port": null,
        "hostname": "domifa.fabrique.social.gouv.fr",
        "hash": null,
        "search": null,
        "query": null,
        "pathname": "/favicon.ico",
        "path": "/favicon.ico",
        "href": "https://domifa.fabrique.social.gouv.fr/favicon.ico"
      },
      "link": "https://domifa.fabrique.social.gouv.fr/favicon.ico",
      "line": "--2021-09-06 09:41:22--  https://domifa.fabrique.social.gouv.fr/favicon.ico",
      "broken": false
    },
    {
      "url": {
        "protocol": "https:",
        "slashes": true,
        "auth": null,
        "host": "domifa.fabrique.social.gouv.fr",
        "port": null,
        "hostname": "domifa.fabrique.social.gouv.fr",
        "hash": null,
        "search": null,
        "query": null,
        "pathname": "/SourceSansPro-Regular.7a9975d8c02d6933c47d.otf",
        "path": "/SourceSansPro-Regular.7a9975d8c02d6933c47d.otf",
        "href": "https://domifa.fabrique.social.gouv.fr/SourceSansPro-Regular.7a9975d8c02d6933c47d.otf"
      },
      "link": "https://domifa.fabrique.social.gouv.fr/SourceSansPro-Regular.7a9975d8c02d6933c47d.otf",
      "line": "--2021-09-06 09:41:22--  https://domifa.fabrique.social.gouv.fr/SourceSansPro-Regular.7a9975d8c02d6933c47d.otf",
      "broken": false
    },
    {
      "url": {
        "protocol": "https:",
        "slashes": true,
        "auth": null,
        "host": "domifa.fabrique.social.gouv.fr",
        "port": null,
        "hostname": "domifa.fabrique.social.gouv.fr",
        "hash": null,
        "search": null,
        "query": null,
        "pathname": "/SourceSansPro-SemiBold.94f13d0e0d1f9443c8ce.otf",
        "path": "/SourceSansPro-SemiBold.94f13d0e0d1f9443c8ce.otf",
        "href": "https://domifa.fabrique.social.gouv.fr/SourceSansPro-SemiBold.94f13d0e0d1f9443c8ce.otf"
      },
      "link": "https://domifa.fabrique.social.gouv.fr/SourceSansPro-SemiBold.94f13d0e0d1f9443c8ce.otf",
      "line": "--2021-09-06 09:41:22--  https://domifa.fabrique.social.gouv.fr/SourceSansPro-SemiBold.94f13d0e0d1f9443c8ce.otf",
      "broken": false
    },
    {
      "url": {
        "protocol": "https:",
        "slashes": true,
        "auth": null,
        "host": "domifa.fabrique.social.gouv.fr",
        "port": null,
        "hostname": "domifa.fabrique.social.gouv.fr",
        "hash": null,
        "search": null,
        "query": null,
        "pathname": "/SourceSansPro-Bold.751d4a14f36df3f4d63c.otf",
        "path": "/SourceSansPro-Bold.751d4a14f36df3f4d63c.otf",
        "href": "https://domifa.fabrique.social.gouv.fr/SourceSansPro-Bold.751d4a14f36df3f4d63c.otf"
      },
      "link": "https://domifa.fabrique.social.gouv.fr/SourceSansPro-Bold.751d4a14f36df3f4d63c.otf",
      "line": "--2021-09-06 09:41:23--  https://domifa.fabrique.social.gouv.fr/SourceSansPro-Bold.751d4a14f36df3f4d63c.otf",
      "broken": false
    },
    {
      "url": {
        "protocol": "https:",
        "slashes": true,
        "auth": null,
        "host": "domifa.fabrique.social.gouv.fr",
        "port": null,
        "hostname": "domifa.fabrique.social.gouv.fr",
        "hash": null,
        "search": null,
        "query": null,
        "pathname": "/SourceSansPro-It.fb96197d794f3be75287.otf",
        "path": "/SourceSansPro-It.fb96197d794f3be75287.otf",
        "href": "https://domifa.fabrique.social.gouv.fr/SourceSansPro-It.fb96197d794f3be75287.otf"
      },
      "link": "https://domifa.fabrique.social.gouv.fr/SourceSansPro-It.fb96197d794f3be75287.otf",
      "line": "--2021-09-06 09:41:23--  https://domifa.fabrique.social.gouv.fr/SourceSansPro-It.fb96197d794f3be75287.otf",
      "broken": false
    },
    {
      "url": {
        "protocol": "https:",
        "slashes": true,
        "auth": null,
        "host": "domifa.fabrique.social.gouv.fr",
        "port": null,
        "hostname": "domifa.fabrique.social.gouv.fr",
        "hash": null,
        "search": null,
        "query": null,
        "pathname": "/styles.ce21530f25edc04622cb.css",
        "path": "/styles.ce21530f25edc04622cb.css",
        "href": "https://domifa.fabrique.social.gouv.fr/styles.ce21530f25edc04622cb.css"
      },
      "link": "https://domifa.fabrique.social.gouv.fr/styles.ce21530f25edc04622cb.css",
      "line": "--2021-09-06 09:41:23--  https://domifa.fabrique.social.gouv.fr/styles.ce21530f25edc04622cb.css",
      "broken": false
    },
    {
      "url": {
        "protocol": "https:",
        "slashes": true,
        "auth": null,
        "host": "domifa.fabrique.social.gouv.fr",
        "port": null,
        "hostname": "domifa.fabrique.social.gouv.fr",
        "hash": null,
        "search": null,
        "query": null,
        "pathname": "/runtime-es2015.694645034e9b56b81dad.js",
        "path": "/runtime-es2015.694645034e9b56b81dad.js",
        "href": "https://domifa.fabrique.social.gouv.fr/runtime-es2015.694645034e9b56b81dad.js"
      },
      "link": "https://domifa.fabrique.social.gouv.fr/runtime-es2015.694645034e9b56b81dad.js",
      "line": "--2021-09-06 09:41:23--  https://domifa.fabrique.social.gouv.fr/runtime-es2015.694645034e9b56b81dad.js",
      "broken": false
    },
    {
      "url": {
        "protocol": "https:",
        "slashes": true,
        "auth": null,
        "host": "domifa.fabrique.social.gouv.fr",
        "port": null,
        "hostname": "domifa.fabrique.social.gouv.fr",
        "hash": null,
        "search": null,
        "query": null,
        "pathname": "/runtime-es5.694645034e9b56b81dad.js",
        "path": "/runtime-es5.694645034e9b56b81dad.js",
        "href": "https://domifa.fabrique.social.gouv.fr/runtime-es5.694645034e9b56b81dad.js"
      },
      "link": "https://domifa.fabrique.social.gouv.fr/runtime-es5.694645034e9b56b81dad.js",
      "line": "--2021-09-06 09:41:23--  https://domifa.fabrique.social.gouv.fr/runtime-es5.694645034e9b56b81dad.js",
      "broken": false
    },
    {
      "url": {
        "protocol": "https:",
        "slashes": true,
        "auth": null,
        "host": "domifa.fabrique.social.gouv.fr",
        "port": null,
        "hostname": "domifa.fabrique.social.gouv.fr",
        "hash": null,
        "search": null,
        "query": null,
        "pathname": "/polyfills-es5.74519c331871e579e362.js",
        "path": "/polyfills-es5.74519c331871e579e362.js",
        "href": "https://domifa.fabrique.social.gouv.fr/polyfills-es5.74519c331871e579e362.js"
      },
      "link": "https://domifa.fabrique.social.gouv.fr/polyfills-es5.74519c331871e579e362.js",
      "line": "--2021-09-06 09:41:23--  https://domifa.fabrique.social.gouv.fr/polyfills-es5.74519c331871e579e362.js",
      "broken": false
    },
    {
      "url": {
        "protocol": "https:",
        "slashes": true,
        "auth": null,
        "host": "domifa.fabrique.social.gouv.fr",
        "port": null,
        "hostname": "domifa.fabrique.social.gouv.fr",
        "hash": null,
        "search": null,
        "query": null,
        "pathname": "/polyfills-es2015.d66cb3c8a0917e0702a1.js",
        "path": "/polyfills-es2015.d66cb3c8a0917e0702a1.js",
        "href": "https://domifa.fabrique.social.gouv.fr/polyfills-es2015.d66cb3c8a0917e0702a1.js"
      },
      "link": "https://domifa.fabrique.social.gouv.fr/polyfills-es2015.d66cb3c8a0917e0702a1.js",
      "line": "--2021-09-06 09:41:24--  https://domifa.fabrique.social.gouv.fr/polyfills-es2015.d66cb3c8a0917e0702a1.js",
      "broken": false
    },
    {
      "url": {
        "protocol": "https:",
        "slashes": true,
        "auth": null,
        "host": "domifa.fabrique.social.gouv.fr",
        "port": null,
        "hostname": "domifa.fabrique.social.gouv.fr",
        "hash": null,
        "search": null,
        "query": null,
        "pathname": "/main-es2015.d4c462093296e2b1f301.js",
        "path": "/main-es2015.d4c462093296e2b1f301.js",
        "href": "https://domifa.fabrique.social.gouv.fr/main-es2015.d4c462093296e2b1f301.js"
      },
      "link": "https://domifa.fabrique.social.gouv.fr/main-es2015.d4c462093296e2b1f301.js",
      "line": "--2021-09-06 09:41:24--  https://domifa.fabrique.social.gouv.fr/main-es2015.d4c462093296e2b1f301.js",
      "broken": false
    },
    {
      "url": {
        "protocol": "https:",
        "slashes": true,
        "auth": null,
        "host": "domifa.fabrique.social.gouv.fr",
        "port": null,
        "hostname": "domifa.fabrique.social.gouv.fr",
        "hash": null,
        "search": null,
        "query": null,
        "pathname": "/main-es5.d4c462093296e2b1f301.js",
        "path": "/main-es5.d4c462093296e2b1f301.js",
        "href": "https://domifa.fabrique.social.gouv.fr/main-es5.d4c462093296e2b1f301.js"
      },
      "link": "https://domifa.fabrique.social.gouv.fr/main-es5.d4c462093296e2b1f301.js",
      "line": "--2021-09-06 09:41:24--  https://domifa.fabrique.social.gouv.fr/main-es5.d4c462093296e2b1f301.js",
      "broken": false
    },
    {
      "url": {
        "protocol": "https:",
        "slashes": true,
        "auth": null,
        "host": "domifa.fabrique.social.gouv.fr",
        "port": null,
        "hostname": "domifa.fabrique.social.gouv.fr",
        "hash": null,
        "search": null,
        "query": null,
        "pathname": "/Evolventa-Regular.bea4dadebf6ff7f13e29.ttf",
        "path": "/Evolventa-Regular.bea4dadebf6ff7f13e29.ttf",
        "href": "https://domifa.fabrique.social.gouv.fr/Evolventa-Regular.bea4dadebf6ff7f13e29.ttf"
      },
      "link": "https://domifa.fabrique.social.gouv.fr/Evolventa-Regular.bea4dadebf6ff7f13e29.ttf",
      "line": "--2021-09-06 09:41:24--  https://domifa.fabrique.social.gouv.fr/Evolventa-Regular.bea4dadebf6ff7f13e29.ttf",
      "broken": false
    },
    {
      "url": {
        "protocol": "https:",
        "slashes": true,
        "auth": null,
        "host": "domifa.fabrique.social.gouv.fr",
        "port": null,
        "hostname": "domifa.fabrique.social.gouv.fr",
        "hash": null,
        "search": null,
        "query": null,
        "pathname": "/Evolventa-Bold.bdd876d18c8ec79d6fbf.ttf",
        "path": "/Evolventa-Bold.bdd876d18c8ec79d6fbf.ttf",
        "href": "https://domifa.fabrique.social.gouv.fr/Evolventa-Bold.bdd876d18c8ec79d6fbf.ttf"
      },
      "link": "https://domifa.fabrique.social.gouv.fr/Evolventa-Bold.bdd876d18c8ec79d6fbf.ttf",
      "line": "--2021-09-06 09:41:24--  https://domifa.fabrique.social.gouv.fr/Evolventa-Bold.bdd876d18c8ec79d6fbf.ttf",
      "broken": false
    },
    {
      "url": {
        "protocol": "https:",
        "slashes": true,
        "auth": null,
        "host": "domifa.fabrique.social.gouv.fr",
        "port": null,
        "hostname": "domifa.fabrique.social.gouv.fr",
        "hash": null,
        "search": null,
        "query": null,
        "pathname": "/plus.d2efee588c8fccad547e.svg",
        "path": "/plus.d2efee588c8fccad547e.svg",
        "href": "https://domifa.fabrique.social.gouv.fr/plus.d2efee588c8fccad547e.svg"
      },
      "link": "https://domifa.fabrique.social.gouv.fr/plus.d2efee588c8fccad547e.svg",
      "line": "--2021-09-06 09:41:24--  https://domifa.fabrique.social.gouv.fr/plus.d2efee588c8fccad547e.svg",
      "broken": false
    },
    {
      "url": {
        "protocol": "https:",
        "slashes": true,
        "auth": null,
        "host": "domifa.fabrique.social.gouv.fr",
        "port": null,
        "hostname": "domifa.fabrique.social.gouv.fr",
        "hash": null,
        "search": null,
        "query": null,
        "pathname": "/moins.ced3dd76dc960c0d0cac.svg",
        "path": "/moins.ced3dd76dc960c0d0cac.svg",
        "href": "https://domifa.fabrique.social.gouv.fr/moins.ced3dd76dc960c0d0cac.svg"
      },
      "link": "https://domifa.fabrique.social.gouv.fr/moins.ced3dd76dc960c0d0cac.svg",
      "line": "--2021-09-06 09:41:24--  https://domifa.fabrique.social.gouv.fr/moins.ced3dd76dc960c0d0cac.svg",
      "broken": false
    },
    {
      "url": {
        "protocol": "https:",
        "slashes": true,
        "auth": null,
        "host": "domifa.fabrique.social.gouv.fr",
        "port": null,
        "hostname": "domifa.fabrique.social.gouv.fr",
        "hash": null,
        "search": null,
        "query": null,
        "pathname": "/courrier.7fcb5658f2d74780580d.svg",
        "path": "/courrier.7fcb5658f2d74780580d.svg",
        "href": "https://domifa.fabrique.social.gouv.fr/courrier.7fcb5658f2d74780580d.svg"
      },
      "link": "https://domifa.fabrique.social.gouv.fr/courrier.7fcb5658f2d74780580d.svg",
      "line": "--2021-09-06 09:41:24--  https://domifa.fabrique.social.gouv.fr/courrier.7fcb5658f2d74780580d.svg",
      "broken": false
    },
    {
      "url": {
        "protocol": "https:",
        "slashes": true,
        "auth": null,
        "host": "domifa.fabrique.social.gouv.fr",
        "port": null,
        "hostname": "domifa.fabrique.social.gouv.fr",
        "hash": null,
        "search": null,
        "query": null,
        "pathname": "/colis.dd8596ff4325ef746ab9.svg",
        "path": "/colis.dd8596ff4325ef746ab9.svg",
        "href": "https://domifa.fabrique.social.gouv.fr/colis.dd8596ff4325ef746ab9.svg"
      },
      "link": "https://domifa.fabrique.social.gouv.fr/colis.dd8596ff4325ef746ab9.svg",
      "line": "--2021-09-06 09:41:24--  https://domifa.fabrique.social.gouv.fr/colis.dd8596ff4325ef746ab9.svg",
      "broken": false
    },
    {
      "url": {
        "protocol": "https:",
        "slashes": true,
        "auth": null,
        "host": "domifa.fabrique.social.gouv.fr",
        "port": null,
        "hostname": "domifa.fabrique.social.gouv.fr",
        "hash": null,
        "search": null,
        "query": null,
        "pathname": "/recommande.09922ec438ef81bd422e.svg",
        "path": "/recommande.09922ec438ef81bd422e.svg",
        "href": "https://domifa.fabrique.social.gouv.fr/recommande.09922ec438ef81bd422e.svg"
      },
      "link": "https://domifa.fabrique.social.gouv.fr/recommande.09922ec438ef81bd422e.svg",
      "line": "--2021-09-06 09:41:24--  https://domifa.fabrique.social.gouv.fr/recommande.09922ec438ef81bd422e.svg",
      "broken": false
    },
    {
      "url": {
        "protocol": "https:",
        "slashes": true,
        "auth": null,
        "host": "domifa.fabrique.social.gouv.fr",
        "port": null,
        "hostname": "domifa.fabrique.social.gouv.fr",
        "hash": null,
        "search": null,
        "query": null,
        "pathname": "/avispassage.c10e0cb84bbfadc37fbd.svg",
        "path": "/avispassage.c10e0cb84bbfadc37fbd.svg",
        "href": "https://domifa.fabrique.social.gouv.fr/avispassage.c10e0cb84bbfadc37fbd.svg"
      },
      "link": "https://domifa.fabrique.social.gouv.fr/avispassage.c10e0cb84bbfadc37fbd.svg",
      "line": "--2021-09-06 09:41:24--  https://domifa.fabrique.social.gouv.fr/avispassage.c10e0cb84bbfadc37fbd.svg",
      "broken": false
    },
    {
      "url": {
        "protocol": "https:",
        "slashes": true,
        "auth": null,
        "host": "domifa.fabrique.social.gouv.fr",
        "port": null,
        "hostname": "domifa.fabrique.social.gouv.fr",
        "hash": null,
        "search": null,
        "query": null,
        "pathname": "/phone.6aa338b8bf5d61b1c17a.svg",
        "path": "/phone.6aa338b8bf5d61b1c17a.svg",
        "href": "https://domifa.fabrique.social.gouv.fr/phone.6aa338b8bf5d61b1c17a.svg"
      },
      "link": "https://domifa.fabrique.social.gouv.fr/phone.6aa338b8bf5d61b1c17a.svg",
      "line": "--2021-09-06 09:41:25--  https://domifa.fabrique.social.gouv.fr/phone.6aa338b8bf5d61b1c17a.svg",
      "broken": false
    },
    {
      "url": {
        "protocol": "https:",
        "slashes": true,
        "auth": null,
        "host": "domifa.fabrique.social.gouv.fr",
        "port": null,
        "hostname": "domifa.fabrique.social.gouv.fr",
        "hash": null,
        "search": null,
        "query": null,
        "pathname": "/passage.f8d201271932411b63c1.svg",
        "path": "/passage.f8d201271932411b63c1.svg",
        "href": "https://domifa.fabrique.social.gouv.fr/passage.f8d201271932411b63c1.svg"
      },
      "link": "https://domifa.fabrique.social.gouv.fr/passage.f8d201271932411b63c1.svg",
      "line": "--2021-09-06 09:41:25--  https://domifa.fabrique.social.gouv.fr/passage.f8d201271932411b63c1.svg",
      "broken": false
    },
    {
      "url": {
        "protocol": "https:",
        "slashes": true,
        "auth": null,
        "host": "domifa.fabrique.social.gouv.fr",
        "port": null,
        "hostname": "domifa.fabrique.social.gouv.fr",
        "hash": null,
        "search": null,
        "query": null,
        "pathname": "/distribution.bbfca7fd68dfafd372b2.svg",
        "path": "/distribution.bbfca7fd68dfafd372b2.svg",
        "href": "https://domifa.fabrique.social.gouv.fr/distribution.bbfca7fd68dfafd372b2.svg"
      },
      "link": "https://domifa.fabrique.social.gouv.fr/distribution.bbfca7fd68dfafd372b2.svg",
      "line": "--2021-09-06 09:41:25--  https://domifa.fabrique.social.gouv.fr/distribution.bbfca7fd68dfafd372b2.svg",
      "broken": false
    },
    {
      "url": {
        "protocol": "https:",
        "slashes": true,
        "auth": null,
        "host": "domifa.fabrique.social.gouv.fr",
        "port": null,
        "hostname": "domifa.fabrique.social.gouv.fr",
        "hash": null,
        "search": null,
        "query": null,
        "pathname": "/reception.3e5571b4f86537f8f131.svg",
        "path": "/reception.3e5571b4f86537f8f131.svg",
        "href": "https://domifa.fabrique.social.gouv.fr/reception.3e5571b4f86537f8f131.svg"
      },
      "link": "https://domifa.fabrique.social.gouv.fr/reception.3e5571b4f86537f8f131.svg",
      "line": "--2021-09-06 09:41:25--  https://domifa.fabrique.social.gouv.fr/reception.3e5571b4f86537f8f131.svg",
      "broken": false
    }
  ],
  "broken": []
}